markitdown_rtf_plugin/__about__.py
markitdown_rtf_plugin/__init__.py
markitdown_rtf_plugin/_plugin.py
markitdown_rtf_plugin/py.typed
markitdown_rtf_plugin-0.1.0.dist-info/METADATA
markitdown_rtf_plugin-0.1.0.dist-info/WHEEL
markitdown_rtf_plugin-0.1.0.dist-info/entry_points.txt
markitdown_rtf_plugin-0.1.0.dist-info/RECORD
