Metadata-Version: 2.4
Name: markitdown-rtf-plugin
Version: 0.1.0
Summary: A RTF plugin via striprtf for the "markitdown" library.
Project-URL: Documentation, https://github.com/microsoft/markitdown#readme
Project-URL: Issues, https://github.com/microsoft/markitdown/issues
Project-URL: Source, https://github.com/microsoft/markitdown
Author-email: Ruslan Belkov <ruslan.belckov@yandex.ru>
License-Expression: MIT
Classifier: Development Status :: 4 - Beta
Classifier: Programming Language :: Python
Classifier: Programming Language :: Python :: 3.10
Classifier: Programming Language :: Python :: 3.11
Classifier: Programming Language :: Python :: 3.12
Classifier: Programming Language :: Python :: 3.13
Classifier: Programming Language :: Python :: Implementation :: CPython
Classifier: Programming Language :: Python :: Implementation :: PyPy
Requires-Python: >=3.10
Requires-Dist: chardet
Requires-Dist: markitdown>=0.1.0a1
Requires-Dist: striprtf
